primenumbers_deprueba/NumerosPrimos.py
primenumbers_deprueba-1.0.dist-info/LICENSE
primenumbers_deprueba-1.0.dist-info/METADATA
primenumbers_deprueba-1.0.dist-info/WHEEL
primenumbers_deprueba-1.0.dist-info/top_level.txt
primenumbers_deprueba-1.0.dist-info/RECORD
